pulumi_azure_nextgen
