Metadata-Version: 2.1
Name: pulumi-azure-nextgen
Version: 0.2.9a1606165683
Summary: A Next Generation Pulumi package for creating and managing Azure resources.
Home-page: https://pulumi.com
License: Apache-2.0
Project-URL: Repository, https://github.com/pulumi/pulumi-azure-nextgen
Keywords: pulumi azure azure-nextgen
Platform: UNKNOWN
